basics/adder/full_adder.v
//full_adder.v

module full_adder (
    input wire a,
    input wire b,
    input wire cin,
    output wire sum,
    output wire cout
);

    assign sum = (a ^ b) ^ cin;
    assign cout = (a & b) | (cin & (a ^ b));

endmodule

basics/adders/full_adder_tb.v
// full_adder_tb.v
`timescale 1ns/1ps

module full_adder_tb;
    reg a;
    reg b;
    reg cin;
    wire sum;
    wire cout;

    full_adder uut (
        .a(a),
        .b(b),
        .cin(cin),
        .sum(sum),
        .cout(cout)
    );

    task test_full_adder;
        input a_t;
        input b_t;
        input cin_t;
        input expected_sum;
        input expected_cout;

        begin
            a = a_t; b = b_t; cin = cin_t;
            #10;

            if(sum != expected_sum || cout != expected_cout) begin
                $display("FAIL: %b + %b cin &b != &b carry %b (got %b carry %b)", a_t, b_t, cin_t, expected_sum, expected_cout, sum, cout);
                $fatal;
            end
        end
    endtask

    initial begin 
        $dumpfile("full_adder.vcd");
        $dumpvars(0, full_adder_tb);

        test_full_adder(0, 0, 0, 0, 0);
        test_full_adder(0, 0, 1, 1, 0);
        test_full_adder(0, 1, 0, 1, 0);
        test_full_adder(0, 1, 1, 0, 1);
        test_full_adder(1, 0, 0, 1, 0);
        test_full_adder(1, 0, 1, 0, 1);
        test_full_adder(1, 1, 0, 0, 1);
        test_full_adder(1, 1, 1, 1, 1);

        $finish;
    end

endmodule

basics/adder/full_adder.vcd
$date
	Mon Apr 21 22:55:52 2025
$end
$version
	Icarus Verilog
$end
$timescale
	1ps
$end
$scope module full_adder_tb $end
$var wire 1 ! sum $end
$var wire 1 " cout $end
$var reg 1 # a $end
$var reg 1 $ b $end
$var reg 1 % cin $end
$scope module uut $end
$var wire 1 # a $end
$var wire 1 $ b $end
$var wire 1 % cin $end
$var wire 1 " cout $end
$var wire 1 ! sum $end
$upscope $end
$scope task test_full_adder $end
$var reg 1 & a_t $end
$var reg 1 ' b_t $end
$var reg 1 ( cin_t $end
$var reg 1 ) expected_cout $end
$var reg 1 * expected_sum $end
$upscope $end
$upscope $end
$enddefinitions $end
$comment Show the parameter values. $end
$dumpall
$end
#0
$dumpvars
0*
0)
0(
0'
0&
0%
0$
0#
0"
0!
$end
#10000
1!
1%
1*
1(
#20000
0%
1$
0(
1'
#30000
1"
0!
1%
1)
0*
1(
#40000
0"
1!
0%
0$
1#
0)
1*
0(
0'
1&
#50000
1"
0!
1%
1)
0*
1(
#60000
0%
1$
0(
1'
#70000
1!
1%
1*
1(
